LICENSE
MANIFEST.in
README.md
setup.cfg
setup.py
mlhub/__init__.py
mlhub/commands.py
mlhub/constants.py
mlhub/pkg.py
mlhub/utils.py
mlhub/bash_completion.d/ml.bash
mlhub/scripts/convert_readme.sh
mlhub/scripts/dep/mlhub.sh
mlhub/scripts/dep/python.sh
mlhub/scripts/dep/r.R
mlhub/scripts/dep/system.sh
mlhub/scripts/dep/utils.sh
mlhubdev.egg-info/PKG-INFO
mlhubdev.egg-info/SOURCES.txt
mlhubdev.egg-info/dependency_links.txt
mlhubdev.egg-info/entry_points.txt
mlhubdev.egg-info/requires.txt
mlhubdev.egg-info/top_level.txt